ChatGPTWeb/ChatGPTWeb.py
ChatGPTWeb/OpenAIAuth.py
ChatGPTWeb/__init__.py
ChatGPTWeb/__main__.py
ChatGPTWeb/api.py
ChatGPTWeb/config.py
ChatGPTWeb/load.js
ChatGPTWeb/load.py
ChatGPTWeb/load2.js
ChatGPTWeb-0.3.3.dist-info/WHEEL
ChatGPTWeb-0.3.3.dist-info/METADATA
ChatGPTWeb-0.3.3.dist-info/licenses/LICENSE
ChatGPTWeb-0.3.3.dist-info/RECORD
