Metadata-Version: 2.1
Name: ChatGPTWeb
Version: 0.3.3
Summary: ChatGPT PlayWright API
License: GPL3
Author-email: nek0us <nekouss@mail.com>
Requires-Python: >=3.10
Requires-Dist: aioconsole
Requires-Dist: aiohttp
Requires-Dist: filetype
Requires-Dist: httpx>=0.28.1
Requires-Dist: pillow
Requires-Dist: playwright_firefox>=1.0.4
Project-URL: Homepage, https://github.com/nek0us/ChatGPT
Project-URL: Repository, https://github.com/nek0us/ChatGPT
